CHANGES.rst
CONTRIBUTORS.rst
MANIFEST.in
README.rst
setup.py
docs/LICENSE.GPL
docs/LICENSE.txt
src/pspolicy/__init__.py
src/pspolicy.homes4.base.egg-info/PKG-INFO
src/pspolicy.homes4.base.egg-info/SOURCES.txt
src/pspolicy.homes4.base.egg-info/dependency_links.txt
src/pspolicy.homes4.base.egg-info/entry_points.txt
src/pspolicy.homes4.base.egg-info/namespace_packages.txt
src/pspolicy.homes4.base.egg-info/not-zip-safe
src/pspolicy.homes4.base.egg-info/requires.txt
src/pspolicy.homes4.base.egg-info/top_level.txt
src/pspolicy/homes4/__init__.py
src/pspolicy/homes4/base/__init__.py
src/pspolicy/homes4/base/configure.zcml
src/pspolicy/homes4/base/migration.py
src/pspolicy/homes4/base/profiles.zcml
src/pspolicy/homes4/base/testing.py
src/pspolicy/homes4/base/profiles/default/jsregistry.xml
src/pspolicy/homes4/base/profiles/default/mailhost.xml
src/pspolicy/homes4/base/profiles/default/metadata.xml
src/pspolicy/homes4/base/profiles/default/properties.xml
src/pspolicy/homes4/base/profiles/default/propertiestool.xml
src/pspolicy/homes4/base/profiles/default/registry.xml
src/pspolicy/homes4/base/profiles/default/tinymce.xml
src/pspolicy/homes4/base/tests/__init__.py
src/pspolicy/homes4/base/tests/test_settings.py
src/pspolicy/homes4/base/tests/test_setup.py