Metadata-Version: 1.1
Name: pspolicy.homes4.base
Version: 0.3
Summary: Plone Policy Add-On for the Homes4 sites.
Home-page: https://github.com/propertyshelf/pspolicy.homes4.base
Author: Propertyshelf, Inc.
Author-email: development@propertyshelf.com
License: gpl
Keywords: plone policy
Platform: UNKNOWN
Classifier: Environment :: Web Environment
Classifier: Operating System :: OS Independent
Classifier: Framework :: Zope2
Classifier: Framework :: Plone
Classifier: Framework :: Plone :: 4.2
Classifier: Framework :: Plone :: 4.3
Classifier: Programming Language :: Python
Classifier: Programming Language :: Python :: 2.6
Classifier: Programming Language :: Python :: 2.7
Classifier: Topic :: Software Development :: Libraries :: Python Modules
